jump_portrait/__init__.py
jump_portrait/fetch.py
jump_portrait/s3.py
jump_portrait/save.py
jump_portrait/utils.py
jump_portrait-0.0.26.dist-info/LICENSE
jump_portrait-0.0.26.dist-info/LICENSE.txt
jump_portrait-0.0.26.dist-info/METADATA
jump_portrait-0.0.26.dist-info/WHEEL
jump_portrait-0.0.26.dist-info/RECORD
