Metadata-Version: 2.1
Name: jump-portrait
Version: 0.0.26
Summary: Tools to fetch and visualize JUMP images
Author: Alan Munoz
Requires-Python: >=3.10,<3.12
Classifier: Programming Language :: Python :: 3
Classifier: Programming Language :: Python :: 3.10
Classifier: Programming Language :: Python :: 3.11
Requires-Dist: boto3 (>=1.33.1)
Requires-Dist: broad-babel (>=0.1.27,<0.2.0)
Requires-Dist: joblib (>=1.3.2,<2.0.0)
Requires-Dist: matplotlib (>=3.8.2,<4.0.0)
Requires-Dist: numpy (<2.0)
Requires-Dist: polars (>=1.5.0)
Requires-Dist: pooch (>=1.7.0,<2.0.0)
Requires-Dist: pyarrow (>=16.1.0)
Requires-Dist: s3fs (>=2024.6.0,<2025.0.0)
Requires-Dist: s3path (>=0.5.0,<0.6.0)
Requires-Dist: tqdm (>=4.66.1,<5.0.0)
